README.rst
setup.py
antimarkdown/__init__.py
antimarkdown/handlers.py
antimarkdown/nodes.py
antimarkdown.egg-info/PKG-INFO
antimarkdown.egg-info/SOURCES.txt
antimarkdown.egg-info/dependency_links.txt
antimarkdown.egg-info/not-zip-safe
antimarkdown.egg-info/requires.txt
antimarkdown.egg-info/top_level.txt